<?xml version="1.0" ?>
<!DOCTYPE PubmedArticleSet PUBLIC "-//NLM//DTD PubMedArticle, 1st January 2024//EN" "https://dtd.nlm.nih.gov/ncbi/pubmed/out/pubmed_240101.dtd">
<PubmedArticleSet>
<PubmedArticle><MedlineCitation Status="MEDLINE" Owner="NLM" IndexingMethod="Automated"><PMID Version="1">39609032</PMID><DateCompleted><Year>2024</Year><Month>11</Month><Day>28</Day></DateCompleted><DateRevised><Year>2024</Year><Month>11</Month><Day>28</Day></DateRevised><Article PubModel="Electronic"><Journal><ISSN IssnType="Electronic">2044-6055</ISSN><JournalIssue CitedMedium="Internet"><Volume>14</Volume><Issue>11</Issue><PubDate><Year>2024</Year><Month>Nov</Month><Day>27</Day></PubDate></JournalIssue><Title>BMJ open</Title><ISOAbbreviation>BMJ Open</ISOAbbreviation></Journal><ArticleTitle>Using normalisation process theory to evaluate the implementation of a digital health intervention in community and secondary care long COVID clinics.</ArticleTitle><Pagination><StartPage>e092824</StartPage><MedlinePgn>e092824</MedlinePgn></Pagination><ELocationID EIdType="doi" ValidYN="Y">10.1136/bmjopen-2024-092824</ELocationID><Abstract><AbstractText Label="OBJECTIVES" NlmCategory="OBJECTIVE">The potential and expected benefits of digital health interventions (DHI) have long been discussed, yet substantial challenges are associated with deploying DHI at scale. Insights are presented concerning the implementation of a DHI consisting of a patient-facing app and a digital dashboard for clinicians providing supported self-management for long COVID to support both clinicians and patients.</AbstractText><AbstractText Label="DESIGN" NlmCategory="METHODS">Qualitative reflexive thematic analysis, mapped against Normalisation Process Theory.</AbstractText><AbstractText Label="SETTING" NlmCategory="METHODS">Fifty-five and a half hours of zoom recordings of meetings between clinicians in community and secondary care long COVID clinics and members of the research team.</AbstractText><AbstractText Label="PARTICIPANTS" NlmCategory="METHODS">Allied health professionals, service delivery managers and members of the core team, including representatives from industry partners.</AbstractText><AbstractText Label="RESULTS" NlmCategory="RESULTS">The DHI fitted with contextual circumstances and the design supported flexibility to suit circumstances in different trusts. The DHI also aligned with existing ways of working.Healthcare professionals worked together to support the implementation of the DHI, requiring flexibility to take account of local circumstances. The DHI was appraised in both positive and negative terms by healthcare professionals. Using DHIs was said to have the potential to complement care but not be a replacement for face-to-face clinical input. The DHI was judged to have demonstrated the potential to affect long-established patterns and organisational structures of engagement between healthcare professionals and patients in terms of access to care.</AbstractText><AbstractText Label="CONCLUSIONS" NlmCategory="CONCLUSIONS">NPT provided a framework for considering both individual agency and the organisation context, enabling reflections to be made at the level of the structure of services as well as people's experiences. The discipline of considering first the context, then the work and finally the practical effects helped place order on the 'mess' involved in the rapid cycle of developing, refining and implementing a DHI in an atypical environment (a pandemic).</AbstractText><CopyrightInformation>&#xa9; Author(s) (or their employer(s)) 2024. Re-use permitted under CC BY. Published by BMJ.</CopyrightInformation></Abstract><AuthorList CompleteYN="Y"><Author ValidYN="Y"><LastName>Stevenson</LastName><ForeName>Fiona A</ForeName><Initials>FA</Initials><Identifier Source="ORCID">0000-0003-2139-2309</Identifier><AffiliationInfo><Affiliation>Research Department of Primary Care and Population Health, University College London, London, UK f.stevenson@ucl.ac.uk.</Affiliation></AffiliationInfo></Author><Author ValidYN="Y"><LastName>Pfeffer</LastName><ForeName>Paul</ForeName><Initials>P</Initials><AffiliationInfo><Affiliation>Department of Respiratory Medicine, Barts Health NHS Trust, London, UK.</Affiliation></AffiliationInfo></Author><Author ValidYN="Y"><LastName>Walker</LastName><ForeName>Sarah</ForeName><Initials>S</Initials><Identifier Source="ORCID">0000-0003-4201-1093</Identifier><AffiliationInfo><Affiliation>University of Exeter Medical School, Exeter, UK.</Affiliation></AffiliationInfo></Author><Author ValidYN="Y"><LastName>Ismaila</LastName><ForeName>Hadiza</ForeName><Initials>H</Initials><AffiliationInfo><Affiliation>University College London, London, UK.</Affiliation></AffiliationInfo></Author><Author ValidYN="Y"><LastName>Jegatheesan</LastName><ForeName>Vinosh</ForeName><Initials>V</Initials><AffiliationInfo><Affiliation>University College London, London, UK.</Affiliation></AffiliationInfo></Author><Author ValidYN="Y"><LastName>Mohammad</LastName><ForeName>Ibrahim</ForeName><Initials>I</Initials><AffiliationInfo><Affiliation>University College London, London, UK.</Affiliation></AffiliationInfo></Author><Author ValidYN="Y"><LastName>Blandford</LastName><ForeName>Ann</ForeName><Initials>A</Initials><Identifier Source="ORCID">0000-0002-3198-7122</Identifier><AffiliationInfo><Affiliation>UCLIC, University College London, London, UK.</Affiliation></AffiliationInfo></Author><Author ValidYN="Y"><LastName>Linke</LastName><ForeName>Stuart</ForeName><Initials>S</Initials><AffiliationInfo><Affiliation>Research Department of Primary Care and Population Health, University College London, London, UK.</Affiliation></AffiliationInfo></Author><Author ValidYN="Y"><LastName>Hurst</LastName><ForeName>John R</ForeName><Initials>JR</Initials><Identifier Source="ORCID">0000-0002-7246-6040</Identifier><AffiliationInfo><Affiliation>Academic Unit of Respiratory Medicine, UCL Medical School, London, UK.</Affiliation></AffiliationInfo></Author><Author ValidYN="Y"><LastName>Ricketts</LastName><ForeName>William</ForeName><Initials>W</Initials><Identifier Source="ORCID">0000-0002-0475-0744</Identifier><AffiliationInfo><Affiliation>Respiratory Medicine, Barts Health NHS Trust, London, UK.</Affiliation></AffiliationInfo></Author><Author ValidYN="Y"><LastName>Hamilton</LastName><ForeName>Fiona L</ForeName><Initials>FL</Initials><AffiliationInfo><Affiliation>Research Department of Primary Care and Population Health, University College London, London, UK.</Affiliation></AffiliationInfo></Author><Author ValidYN="Y"><LastName>Sunkersing</LastName><ForeName>David</ForeName><Initials>D</Initials><AffiliationInfo><Affiliation>Institute of Health Informatics, University College London, London, UK.</Affiliation></AffiliationInfo></Author><Author ValidYN="Y"><LastName>Bradbury</LastName><ForeName>Katherine</ForeName><Initials>K</Initials><AffiliationInfo><Affiliation>Psychology, University of Southampton, Southampton, UK.</Affiliation></AffiliationInfo></Author><Author ValidYN="Y"><LastName>Goodfellow</LastName><ForeName>Henry</ForeName><Initials>H</Initials><Identifier Source="ORCID">0000-0002-0979-2839</Identifier><AffiliationInfo><Affiliation>Research Department of Primary Care and Population Health, University College London, London, UK.</Affiliation></AffiliationInfo></Author></AuthorList><Language>eng</Language><PublicationTypeList><PublicationType UI="D016428">Journal Article</PublicationType></PublicationTypeList><ArticleDate DateType="Electronic"><Year>2024</Year><Month>11</Month><Day>27</Day></ArticleDate></Article><MedlineJournalInfo><Country>England</Country><MedlineTA>BMJ Open</MedlineTA><NlmUniqueID>101552874</NlmUniqueID><ISSNLinking>2044-6055</ISSNLinking></MedlineJournalInfo><CitationSubset>IM</CitationSubset><MeshHeadingList><MeshHeading><DescriptorName UI="D006801" MajorTopicYN="N">Humans</DescriptorName></MeshHeading><MeshHeading><DescriptorName UI="D000086382" MajorTopicYN="Y">COVID-19</DescriptorName><QualifierName UI="Q000453" MajorTopicYN="N">epidemiology</QualifierName></MeshHeading><MeshHeading><DescriptorName UI="D063127" MajorTopicYN="Y">Secondary Care</DescriptorName><QualifierName UI="Q000458" MajorTopicYN="N">organization &amp; administration</QualifierName></MeshHeading><MeshHeading><DescriptorName UI="D017216" MajorTopicYN="Y">Telemedicine</DescriptorName><QualifierName UI="Q000458" MajorTopicYN="N">organization &amp; administration</QualifierName></MeshHeading><MeshHeading><DescriptorName UI="D036301" MajorTopicYN="N">Qualitative Research</DescriptorName></MeshHeading><MeshHeading><DescriptorName UI="D000086402" MajorTopicYN="N">SARS-CoV-2</DescriptorName></MeshHeading><MeshHeading><DescriptorName UI="D003153" MajorTopicYN="N">Community Health Services</DescriptorName><QualifierName UI="Q000458" MajorTopicYN="N">organization &amp; administration</QualifierName></MeshHeading><MeshHeading><DescriptorName UI="D000094024" MajorTopicYN="N">Post-Acute COVID-19 Syndrome</DescriptorName></MeshHeading><MeshHeading><DescriptorName UI="D000073278" MajorTopicYN="N">Self-Management</DescriptorName><QualifierName UI="Q000379" MajorTopicYN="N">methods</QualifierName></MeshHeading><MeshHeading><DescriptorName UI="D063731" MajorTopicYN="N">Mobile Applications</DescriptorName></MeshHeading><MeshHeading><DescriptorName UI="D000097103" MajorTopicYN="N">Digital Health</DescriptorName></MeshHeading></MeshHeadingList><KeywordList Owner="NOTNLM"><Keyword MajorTopicYN="N">COVID-19</Keyword><Keyword MajorTopicYN="N">Digital Technology</Keyword><Keyword MajorTopicYN="N">Organisation of health services</Keyword><Keyword MajorTopicYN="N">QUALITATIVE RESEARCH</Keyword><Keyword MajorTopicYN="N">eHealth</Keyword></KeywordList><CoiStatement>Competing interests: &#x2018;Yes, there are competing interests for one or more authors and I have provided a Competing Interests statement in my manuscript and in the box below&#x2019;.</CoiStatement></MedlineCitation><PubmedData><History><PubMedPubDate PubStatus="medline"><Year>2024</Year><Month>11</Month><Day>29</Day><Hour>5</Hour><Minute>22</Minute></PubMedPubDate><PubMedPubDate PubStatus="pubmed"><Year>2024</Year><Month>11</Month><Day>29</Day><Hour>5</Hour><Minute>21</Minute></PubMedPubDate><PubMedPubDate PubStatus="entrez"><Year>2024</Year><Month>11</Month><Day>28</Day><Hour>21</Hour><Minute>25</Minute></PubMedPubDate></History><PublicationStatus>epublish</PublicationStatus><ArticleIdList><ArticleId IdType="pubmed">39609032</ArticleId><ArticleId IdType="doi">10.1136/bmjopen-2024-092824</ArticleId><ArticleId IdType="pii">bmjopen-2024-092824</ArticleId></ArticleIdList></PubmedData></PubmedArticle></PubmedArticleSet>